{"name":"Month Picker","tagline":"A simple yet good looking JavaScript month picker","body":"Dependencies\r\n------------\r\n\r\nNone (so far).\r\n\r\nHow to use it\r\n-------------\r\n\r\n```javascript\r\nvar monthPicker = new MonthPicker();\r\n\r\ndocument.body.appendChild(monthPicker.el);\r\n\r\nmonthPicker.model().on('change', function() {\r\n  var year = monthPicker.model().get('year');\r\n  var month = monthPicker.model().get('month');\r\n  \r\n  console.log('year:', year);\r\n  console.log('month:', month);\r\n});\r\n```","google":"","note":"Don't delete this file! It's used internally to help with page regeneration."}